openide_client/__init__.py
openide_client/cli.py
openide_client/client.py
openide_client/client_backup.py
openide_client-1.1.2.dist-info/METADATA
openide_client-1.1.2.dist-info/WHEEL
openide_client-1.1.2.dist-info/entry_points.txt
openide_client-1.1.2.dist-info/top_level.txt
openide_client-1.1.2.dist-info/RECORD
