Metadata-Version: 2.4
Name: openide-client
Version: 1.1.2
Summary: Python client library for OpenIDE container system
Home-page: https://github.com/artemjs/OpenIDE/tree/openide-client
Author: ArtemJS
Author-email: ArtemJS <artemjson@gmail.com>
Project-URL: Homepage, https://github.com/artemjs/OpenIDE/tree/openide-client
Project-URL: Repository, https://github.com/artemjs/OpenIDE/tree/openide-client
Project-URL: Bug Reports, https://github.com/artemjs/OpenIDE/issues
Keywords: openide,container,docker,development,ide,python,client
Classifier: Development Status :: 4 - Beta
Classifier: Intended Audience :: Developers
Classifier: License :: OSI Approved :: MIT License
Classifier: Operating System :: OS Independent
Classifier: Programming Language :: Python :: 3
Classifier: Programming Language :: Python :: 3.7
Classifier: Programming Language :: Python :: 3.8
Classifier: Programming Language :: Python :: 3.9
Classifier: Programming Language :: Python :: 3.10
Classifier: Programming Language :: Python :: 3.11
Classifier: Programming Language :: Python :: 3.12
Classifier: Programming Language :: Python :: 3.13
Classifier: Topic :: Software Development :: Libraries :: Python Modules
Classifier: Topic :: System :: Systems Administration
Classifier: Topic :: Utilities
Requires-Python: >=3.7
Requires-Dist: requests>=2.28.1
Requires-Dist: click>=8.0.0
Requires-Dist: psutil>=5.9.0
Requires-Dist: colorama>=0.4.4
Requires-Dist: python-dotenv>=0.19.0
Requires-Dist: pyyaml>=6.0
Dynamic: author
Dynamic: home-page
Dynamic: requires-python
